zen_queries/__init__.py
zen_queries/decorators.py
zen_queries/render.py
zen_queries/rest_framework.py
zen_queries/template_response.py
zen_queries/utils.py
zen_queries/templatetags/__init__.py
zen_queries/templatetags/zen_queries.py
zen_queries/tests/__init__.py
zen_queries/tests/models.py
zen_queries/tests/settings.py
zen_queries/tests/tests.py
zen_queries/tests/templates/queries_dangerously_enabled_tag.html
zen_queries/tests/templates/queries_disabled_tag.html
zen_queries/tests/templates/template.html
django_zen_queries-2.1.0.dist-info/LICENSE
django_zen_queries-2.1.0.dist-info/METADATA
django_zen_queries-2.1.0.dist-info/WHEEL
django_zen_queries-2.1.0.dist-info/top_level.txt
django_zen_queries-2.1.0.dist-info/RECORD
