Metadata-Version: 2.1
Name: django-zen-queries
Version: 2.1.0
Summary: Explicit control over query execution in Django applications.
Home-page: https://github.com/dabapps/django-zen-queries
Author: DabApps
Author-email: hello@dabapps.com
License: BSD
Project-URL: Changelog, https://github.com/dabapps/django-zen-queries/releases
Project-URL: Issues, https://github.com/dabapps/django-zen-queries/issues
Platform: UNKNOWN
Requires-Python: >=3.6
